MIDASpy/__init__.py
MIDASpy/midas_base.py
MIDASpy-1.3.1.dist-info/LICENSE.txt
MIDASpy-1.3.1.dist-info/METADATA
MIDASpy-1.3.1.dist-info/WHEEL
MIDASpy-1.3.1.dist-info/top_level.txt
MIDASpy-1.3.1.dist-info/RECORD
