Metadata-Version: 2.1
Name: MIDASpy
Version: 1.3.1
Summary: Multiple Imputation with Denoising Autoencoders
Home-page: http://github.com/MIDASverse/MIDASpy
Author: Ranjit Lall, Alex Stenlake, and Thomas Robinson
Author-email: R.Lall@lse.ac.uk
License: Apache
Project-URL: Method article, https://doi.org/10.1017/pan.2020.49
Project-URL: Software article, https://doi.org/10.18637/jss.v107.i09
Project-URL: Source, https://github.com/MIDASverse/MIDASpy
Project-URL: Issues, https://github.com/MIDASverse/MIDASpy/issues
Keywords: multiple imputation,neural networks,tensorflow
Classifier: Development Status :: 5 - Production/Stable
Classifier: Intended Audience :: Science/Research
Classifier: Topic :: Scientific/Engineering
Classifier: License :: OSI Approved :: Apache Software License
Classifier: Programming Language :: Python :: 3
Classifier: Programming Language :: Python :: 3.6
Classifier: Programming Language :: Python :: 3.7
Classifier: Programming Language :: Python :: 3.8
Classifier: Programming Language :: Python :: 3.9
Classifier: Programming Language :: Python :: 3.10
Requires-Python: >=3.6, <3.11
License-File: LICENSE.txt
Requires-Dist: numpy (>=1.5)
Requires-Dist: scikit-learn
Requires-Dist: matplotlib
Requires-Dist: pandas (>=0.19)
Requires-Dist: tensorflow-addons (<0.20)
Requires-Dist: statsmodels
Requires-Dist: scipy
Requires-Dist: tensorflow (<2.12.0) ; sys_platform != "darwin" or platform_machine != "arm64"
Requires-Dist: tensorflow-macos (<2.12.0) ; sys_platform == "darwin" and platform_machine == "arm64"
Provides-Extra: test
Requires-Dist: pytest ; extra == 'test'
Requires-Dist: matplotlib ; extra == 'test'
